{
    "paper_title": "Toward Physically Consistent Driving Video World Models under Challenging Trajectories",
    "authors": [
        "Jiawei Zhou",
        "Zhenxin Zhu",
        "Lingyi Du",
        "Linye Lyu",
        "Lijun Zhou",
        "Zhanqian Wu",
        "Hongcheng Luo",
        "Zhuotao Tian",
        "Bing Wang",
        "Guang Chen",
        "Hangjun Ye",
        "Haiyang Sun",
        "Yu Li"
    ],
    "sections": [
        {
            "title": "Abstract",
            "content": "Video generation models have shown strong potential as world models for autonomous driving simulation. However, existing approaches are primarily trained on real-world driving datasets, which mostly contain natural and safe driving scenarios. As a result, current models often fail when conditioned on challenging or counterfactual trajectories-such as imperfect trajectories generated by simulators or planning systems-producing videos with severe physical inconsistencies and artifacts. To address this limitation, we propose PhyGenesis, a world model designed to generate driving videos with high visual fidelity and strong physical consistency. Our framework consists of two key components: (1) a physical condition generator that transforms potentially invalid trajectory inputs into physically plausible conditions, and (2) a physics-enhanced video generator that produces high-fidelity multi-view driving videos under these conditions. To effectively train these components, we construct a large-scale, physics-rich heterogeneous dataset. Specifically, in addition to real-world driving videos, we generate diverse challenging driving scenarios using the CARLA simulator, from which we derive supervision signals that guide the model to learn physically grounded dynamics under extreme conditions. This challenging-trajectory learning strategy enables trajectory correction and promotes physically consistent video generation. Extensive experiments demonstrate that PhyGenesis consistently outperforms state-of-the-art methods, especially on challenging trajectories. Our project page is available at: https://wm-research.github.io/PhyGenesis/."
        },
        {
            "title": "Start",
            "content": "6 2 0 2 5 2 ] . [ 1 6 0 5 4 2 . 3 0 6 2 : r a"
        },
        {
            "title": "Toward Physically Consistent Driving Video\nWorld Models under Challenging Trajectories",
            "content": "Jiawei Zhou1,2, Zhenxin Zhu2, Lingyi Du1, Linye Lyu3, Lijun Zhou2, Zhanqian Wu2, Hongcheng Luo2, Zhuotao Tian4, Bing Wang2, Guang Chen2, Hangjun Ye2#, Haiyang Sun2, and Yu Li1# 1 Zhejiang University 2 Xiaomi EV 3 The Hong Kong Polytechnic University 4 Shenzhen Loop Area Institute Fig. 1: Qualitative comparison of video generation under diverse trajectory conditions (front view of the multi-view outputs is shown). Prior methods (e.g., DiST-4D) exhibit artifacts and geometric distortions under physically challenging trajectories, whereas PhyGenesis preserves physical consistency and high visual fidelity. Additional videos are provided in the supplementary material. Equal Contribution. Email: zhoujiawei6666@gmail.com Project Leader. Email: sunhaiyang1@xiaomi.com # Corresponding Author. Email: yu.li.sallylee@gmail.com 2 J. Zhou et al. Abstract. Video generation models have shown strong potential as world models for autonomous driving simulation. However, existing approaches are primarily trained on real-world driving datasets, which mostly contain natural and safe driving scenarios. As result, current models often fail when conditioned on challenging or counterfactual trajectoriessuch as imperfect trajectories generated by simulators or planning systemsproducing videos with severe physical inconsistencies and artifacts. To address this limitation, we propose PhyGenesis, world model designed to generate driving videos with high visual fidelity and strong physical consistency. Our framework consists of two key components: (1) physical condition generator that transforms potentially invalid trajectory inputs into physically plausible conditions, and (2) physicsenhanced video generator that produces high-fidelity multi-view driving videos under these conditions. To effectively train these components, we construct large-scale, physics-rich heterogeneous dataset. Specifically, in addition to real-world driving videos, we generate diverse challenging driving scenarios using the CARLA simulator, from which we derive supervision signals that guide the model to learn physically grounded dynamics under extreme conditions. This challenging-trajectory learning strategy enables trajectory correction and promotes physically consistent video generation. Extensive experiments demonstrate that PhyGenesis consistently outperforms state-of-the-art methods, especially on challenging trajectories. Our project page is available at: https://wmresearch.github.io/PhyGenesis/. Keywords: Autonomous driving World models Video generation"
        },
        {
            "title": "Introduction",
            "content": "Video world models have recently emerged as central paradigm for autonomous driving research [1, 11, 14, 19, 20, 28], offering scalable alternative to expensive real-world data collection and high-fidelity physical simulators. Recent driving world models [3, 4, 9, 15, 35, 43, 45] can synthesize high-fidelity multi-view future scenes while preserving controllability through structured conditions such as vehicle trajectories. These capabilities have enabled variety of downstream applications, including closed-loop evaluation in simulation [38, 42], high-risk scenario synthesis [37, 46], and integration with end-to-end planners for decision making and motion forecasting [26, 29, 36, 44]. Despite these advances, current driving world models struggle when deployed under challenging trajectory conditions produced by trajectory simulators, planning systems, or user interactions. We identify two fundamental limitations of existing approaches. First, current models lack physical awareness of trajectory feasibility. Trajectory conditions generated by simulators or planners can be imperfect and may violate fundamental physical constraints. However, existing models lack explicit physical reasoning and largely behave as conditionto-pixel translators. When forced to follow such physically inconsistent inputs, they often produce videos with severe rendering artifacts and structural failures. PhyGenesis: Physically Consistent Driving Video World Models 3 Second, current models lack physics-consistent generation capability. Most existing approaches [4, 9, 9, 15, 35] are predominantly trained on real-world driving datasets dominated by safe and nominal behaviors. Consequently, they struggle to generate realistic dynamics in rare scenarios such as collisions or offroad departureseven when the trajectories themselves are physically feasible. Consequently, prior approaches (e.g., DiST-4D) often produce severe artifacts and physically inconsistent videos, as shown in Fig. 1. In this work, we introduce PhyGenesis, physics-aware driving world model designed to address both limitations. Our key insight is that physically consistent world modeling requires joint handling of trajectory feasibility and physicsconsistent video generation. To this end, PhyGenesis introduces novel module called the Physical Condition Generator , which transforms arbitrary trajectory conditions into physically consistent ones by resolving potential physical conflicts. The rectified conditions are then fed into Physics-enhanced Video Generator , which synthesizes high-fidelity and physically consistent multi-view driving videos. To support this learning process, we construct heterogeneous training dataset that combines real-world driving data with physically challenging dataset generated using the CARLA simulator [5]. While real-world data provides abundant nominal driving behaviors, the CARLA-generated dataset introduces diverse extreme scenarios such as collisions and off-road departures. These events are uniquely informative, providing dense supervision for learning complex objectenvironment interactionspriors that are fundamentally scarce in routine real-world driving data. With these designs, PhyGenesis substantially outperforms prior methods, particularly under challenging trajectory conditions. Our main contributions are summarized as follows: We propose PhyGenesis, physics-aware driving world model for highfidelity and physically consistent autonomous video generation. By explicitly handling both trajectory feasibility and physics-consistent video generation, PhyGenesis is the first framework capable of synthesizing physically consistent multi-view driving videos even when conditioned on initially physicsviolating trajectory inputs. We introduce Physical Condition Generator that converts arbitrary trajectory inputs into physically feasible 6-DoF vehicle motions. To enable this capability, we formulate novel counterfactual trajectory rectification training task that equips the model with intrinsic physical priors for resolving physics-violating trajectories. We develop Physics-Enhanced Video Generator and train these models on heterogeneous physics-rich dataset combining real-world driving logs with physically extreme synthetic scenarios generated with the CARLA simulator. This hybrid training paradigm enables the model to learn complex objectenvironment interactions and significantly improves video generation under challenging trajectory conditions. 4 J. Zhou et al."
        },
        {
            "title": "2 Related Work",
            "content": "Nominal Driving World Models. Driving video generation has progressed rapidly, with most methods conditioning on structured spatial priors for controllability. BEVGen [31] encodes road and vehicle layouts via BEV maps but discards height information, limiting 3D representational capacity. BEVControl [40] partially addresses this by introducing height-lifting module to restore scene geometry. MagicDrive [10] further advances 3D-aware generation through geometric constraints and cross-view attention, while MagicDrive-V2 [9] adopts Diffusion Transformers for higher-resolution, temporally coherent synthesis. DriveDreamer [34] introduces hybrid Gaussians for temporally consistent complex maneuver rendering. DiST-4D [14] and WorldSplat [47] incorporate metric depth to lift generated videos into 4D scene representations for novel viewpoint synthesis. In the multimodal direction, Genesis [15] and UniScene [23] target joint LiDARRGB generation via sequential DiT and occupancy-centric voxel representations, respectively. While these methods achieve high fidelity under routine driving, their reliance on nominal datasets limits robustness to challenging and/or physics-violating trajectory inputs. High-risk Driving Video Generation. Generating high-risk driving scenarios has attracted growing attention. Early efforts such as AVD2 [24], DrivingGen [16], and Ctrl-Crash [13] synthesize accident scenarios from single-view dashcam footage; however, their single-view, low-quality data making it difficult for models trained on these datasets to transfer to high-fidelity, multi-view simulators. More recent methods, SafeMVDrive [46] and Challenger [37], combine trajectory simulators with multi-view video generators to produce safety-critical videos. Nevertheless, their video generators are trained exclusively on nominal data, so the resulting quality remains limited and the generated scenes cannot depict physical interactions such as collisions. In summary, existing driving world models handle either nominal scenarios or high-risk synthesis, but rarely both. PhyGenesis bridges this gap through Physical Condition Generator and Physics-Enhanced Video Generator trained on both real-world and simulation-derived extreme data."
        },
        {
            "title": "3.1 Overview of PhyGenesis",
            "content": "The overview of our PhyGenesis framework is illustrated in Figure 2. As shown in (a), our framework is trained on heterogeneous multi-view dataset (Section 3.2), which enables the model to learn both high visual fidelity and physical consistency, even under challenging scenarios. Given trajectory inputs, the Physical Condition Generator (Section 3.3) first rectifies potentially invalid trajectories into physically consistent 6-DoF vehicle motions. These rectified conditions are then passed to the Physics-Enhanced Multi-view Video Generator (PE-MVGen) (Section 3.4), which synthesizes multi-view video sequences. This unified pipeline PhyGenesis: Physically Consistent Driving Video World Models 5 Fig. 2: Overview of PhyGenesis. (a) Our heterogeneous multi-view dataset consists of both real-world driving data and simulated data that emphasizes physically challenging scenarios, including ego-vehicle collisions and roadway departures, among others. (b) In PhyGenesis, the physical condition generator first rectifies arbitrary 2D trajectoriespotentially counterfactual or physics-violatinginto physically plausible 6-DoF motions. The rectified trajectories are then projected into camera-view layout conditions and fed into physics-enhanced video generator, co-trained on the heterogeneous dataset, to synthesize high-fidelity, physically consistent multi-view videos. enables high quality video generation even when the input trajectories violate physical constraints. i i,t }T = {T orig i=1, where orig }N Specifically, our system takes as inputs the initial multi-view images I0, static map M, and set of future trajectories orig for all agents, i.e., cars. We define orig = {T orig i,t = (xi,t, yi,t) specifies the 2D location of agent at time t. This 2D trajectory representation orig aligns with the standard output format of mainstream trajectory simulators and end-to-end autonomous driving planners. Crucially, these trajectories can be physics-violating (e.g., containing overlapping paths that would cause object penetration). Given such potentially flawed inputs, our goal is to synthesize high-fidelity, multi-view video sequence V1:T that faithfully reflects the intended driving behaviors while adhering to real-world physical constraints. Next, we detail each part of our design. t=1 and orig"
        },
        {
            "title": "3.2 Heterogeneous Multi-view Data",
            "content": "Real-World Multi-view Data. Following the recent multi-view driving world models [9, 45], we utilize nominal real-world driving logs from the nuScenes dataset [2] to establish foundational understanding of complex urban environments. However, these data are heavily biased towards safe driving behaviors 6 J. Zhou et al. and inherently lack complex physical interactions (e.g. collisions, off-road driving). This data deficiency causes generative models to produce artifacts and physically inconsistent motion under physically challenging trajectories. Simulated Physically-challenging Multi-view Data. To empower world model with robust physical understanding and the capability to generate videos under physically challenging interactions, training data that explicitly contains such events is essential. Since collecting safety-critical real-world data is impractical, modern driving simulators (e.g., CARLA [5]) provide high-fidelity physics engines and controllable environmental variations. Prior work like ReSim [39] has attempted to incorporate synthetic data into world-model training to mitigate the limited coverage of real-world distributions. Their synthetic data is limited to single view with only ego-trajectory annotations, which makes it difficult to train models that control multiple agents. Moreover, their data collection is not explicitly focused on physically challenging events, providing limited supervision for strengthening models physical priors. To fill this gap, we leverage the CARLA simulator to build large-scale multiview synthetic dataset focused on physically challenging scenarios. We follow the Bench2Drive routing setup [22] to cover diverse scenes, weather, and traffic events. Based on this foundation, we curate two subsets: CARLA Ego, capturing interactions between the ego vehicle and the environment or surrounding agents, and CARLA Adv, capturing interactions centered on nearby non-ego agent. During collection, we perturb the route and target speed of the ego vehicle (or the Adv agent) to induce collisions, off-road departures, and abrupt maneuvers (Detailed in supplementary material). This results in substantially more aggressive dynamics than nuScenes, as reflected by the shifted maximum ego-acceleration distribution in Figure 3. We equip the simulation with sensor suite rigorously aligned with the nuScenes configuration, comprising 1 LiDAR, 6 surround-view cameras (900 1600 resolution), 5 radars, and 1 IMU/GNSS unit. Crucially, to accurately capture physical anomalies, we additionally integrate collision sensor and highdefinition (HD) map metadata, allowing us to precisely record the exact timestamps of impacts and off-road moments. The data is recorded at 12Hz and is meticulously annotated and organized into format identical to the nuScenes dataset to ensure seamless downstream training. Heterogeneous Dataset Construction. In total, we simulated approximately 31 hours of driving data. The CARLA-Adv subset contains 15.5 hours with 760K annotated bounding boxes, while the CARLA-Ego subset comprises 15.2 hours with 830K boxes. Utilizing explicit collision sensor signals and map metadata, we design rule-based filtering mechanism to precisely localize timestamps of physical interactions, extracting 9.7 hours of highly physically-challenging video clips. Finally, we combine these 9.7 hours of simulated clips with 4.6 hours of real-world data to construct our heterogeneous dataset. PhyGenesis: Physically Consistent Driving Video World Models 7 Fig. 3: Distributions of maximum ego-vehicle acceleration for nuScenes, CARLA Ego, and CARLA ADV. The simulated CARLA datasets show clear shift toward higher accelerations, indicating more aggressive dynamics and physically challenging events compared with the predominantly nominal driving behaviors in nuScenes. Fig. 4: Comparison of MLP and time-wise output head in simulating collision dynamics. The MLP shows gradual velocity decrease after the collision, while the GT and time-wise head show an instantaneous drop to zero, producing more realistic dynamics."
        },
        {
            "title": "3.3 Physical Condition Generator",
            "content": "Since rendering videos from physics-violating 2D layouts often causes severe artifacts (e.g., distortion or melting), we introduce Physical Condition Generator as the first stage of our framework. Its dynamically rectify the possibly physicalviolating -frame 2D trajectories orig into physically plausible 6-DoF trajectory sequence ˆT 6dof. The transition to 6-DoF (including x, y, z, pitch, yaw, roll) is crucial, as extreme physical interactions often induce drastic variations in the vertical and rotational axes that 2D coordinates cannot capture. Architecture. The architecture of the physical model is illustrated in the left of Figure 2 (b). For given scenario, the input trajectories orig are encoded via sinecosine positional encoding followed by an MLP encoder into agent tokens RN D, where denotes the number of agents and is the token dimension. To ensure that these agents interact reasonably with the visual environment, we first apply deformable spatial cross-attention to interact with the multi-view Perspective View (PV) features Fpv based on their trajectory coordinates. This operation yields the spatially grounded queries qs: qs = SpatialCrossAttn(q, Fpv) (1) Subsequently, an agent-agent self-attention layer is introduced to enable the tokens to perceive the positional and kinematic states of surrounding vehicles, 8 J. Zhou et al. which is the key design for resolving overlapping and penetration conflicts: qa = AgentSelfAttn(qs) (2) Furthermore, map cross-attention layer integrates vectorized map embeddings Emap for better off-road awareness: qm = MapCrossAttn(qa, Emap) (3) Finally, Feed-Forward Network is applied to non-linearly transform the aggregated features, yielding the fully refined queries qf before trajectory prediction: qf = FFN(qm) (4) Following the above layers, the refined queries need to be projected into the final trajectories. Traditional MLPs typically smooth out trajectory outputs, failing to capture the sudden, high-frequency dynamic impulses indicative of collision. To address this, we specifically design Time-Wise Output Head as the final prediction module. For the i-th refined agent token qf [i], we expand it across the future steps and concatenate it with step-specific learnable temporal embedding Etime(t). The concatenated feature is then processed by Temporal Convolutional Network (TCN) to capture local inter-step dynamic variations, before being projected by an MLP to output the exact 6-DoF state: hi,t = TCN (Proj(qf [i] Etime(t))) ˆT 6dof i,t = MLP(hi,t) (5) (6) As shown in Figure 4, unlike standard regression heads that produce sluggish responses, this time-wise formulation paired with step-specific time embeddings accurately captures the abrupt physical changes at the physical impact moment. Training Pair Construction. To equip the Physical Condition Generator with the ability to rectify physics-violating trajectory conditions, we construct paired training data that maps physics-violating trajectory inputs to physically feasible targets. To achieve this, we propose systematic counterfactual trajectory corruption strategy. Specifically, for collision clip in our simulated dataset, we keep the original trajectory logs before the collision. For the post-collision frames, we intentionally corrupt the trajectories of all agents by extending their path with the same velocity before the collision, which synthesizes penetration-style counterfactual trajectory conditions. The ground-truth simulation logswhich capture the actual collision dynamicsserve as the supervision target for correction. In addition, to avoid distorting natural driving conditions, we also include real-world nominal trajectory-condition pairs from nuScenes without applying counterfactual corruption, ensuring the model preserves realistic inputs while learning to rectify physically invalid ones. PhyGenesis: Physically Consistent Driving Video World Models 9 Optimization. The Physical Model is optimized using weighted distance loss between the predicted 6-DoF trajectories and the ground truth: Tphy ="
        },
        {
            "title": "1\nN × T",
            "content": "N (cid:88) (cid:88) i=1 t=1 Wi,t (cid:13) ˆT 6dof i,t gt (cid:13) (cid:13) i,t (cid:13) (cid:13) (cid:13)1 (7) To focus on critical physical moments, we define Wi,t with two scalars: an eventwindow weight λevent that increases the loss within temporal window around collision/off-road timesteps, and physical-agent weight λagent that further amplifies the loss for agents involved in the interaction."
        },
        {
            "title": "3.4 Physics-Enhanced Multi-view Video Generator",
            "content": "The second stage of our framework is the Physics-Enhanced Multi-View Video Generator (PE-MVGen). Built upon Wan2.1 [33], high-capacity diffusion transformer (DiT) originally conditioned on images and text, we adapt it into controllable, multi-view generator explicitly designed for the autonomous driving domain. Crucially, this generator is endowed with deep physical awareness through specialized heterogeneous co-training strategy. Multi-View & Layout Conditioning. We first encode the input multi-view clips into latents RV Chw using pre-trained 3D VAE [33], where represents the number of views. To enable multi-view modeling without introducing additional parameters [9, 35], we reshape the input into (V w), concatenating the view dimension into the spatial axis so that the same selfattention can capture cross-view dependencies. Furthermore, to explicitly condition generation on structural layouts, we project the future -frame 3D agent boxes and map polylines onto each camera view using the calibrated intrinsics Kv and extrinsics Ev. The resulting view-specific control images Mv are encoded by the VAE encoder to get zc , reshaped to match the video latents, concatenated along the channel dimension with the noisy latent input zt, and finally processed by patch embedder before entering the DiT. Data-Driven Physical Enhancement. Current world models fail in physically challenging scenarios because their training distributions lack physical interactions. To solve this, we train PE-MVGen on our heterogeneous dataset, maintaining balanced 1:1 ratio between nominal real-world logs and simulated physically challenging data. Crucially, we do not use counterfactual trajectories at this stage; the generator is supervised with ground-truth physical trajectories, decoupling physical correction from rendering. As demonstrated in Figure 10, co-training with this physics-rich data significantly enhances the models physical understanding, allowing its generative capabilities to robustly generalize to physically challenging scenarios in real-world. [8, 12] Training Objective. Following Wan 2.1, PE-MVGen is optimized via Rectified Flows [7], which ensures stable training through ordinary differential equations (ODEs). During training, given clean video latent z1, random noise z0 (0, I), and timestep [0, 1] sampled from logit-normal distribution, the 10 J. Zhou et al. intermediate noisy latent zt is defined as linear interpolation: zt = tz1 + (1 t)z0 (8) The ground-truth velocity vector is defined as vt = z1 z0. The DiT model, parameterized by θ, is trained to predict this velocity uθ. The flow-matching objective is formulated as the Mean Squared Error (MSE): LF = Ez0,z1,t uθ(zt, t, cinit, ctext, clayout) vt2 2 (9) where the predicted velocity uθ is conditioned on three key components: cinit denotes the latent features of single initial context frame, ctext represents the scene caption, and clayout encodes the future multi-view layout images. Curriculum Co-Training Strategy. We adopt highly efficient two-stage curriculum: pre-training at lower resolution (224 400) to quickly learn multiview geometry and physically challenging layout mappings, followed by highresolution (448 800) fine-tuning to ensure visual fidelity."
        },
        {
            "title": "4.1 Experimental Setup",
            "content": "Datasets: We use the heterogeneous multi-view dataset introduced in Section 3.2, including CARLA Ego, CARLA ADV, and nuScenes, for training and evaluation. During training, we adopt balanced sampling to keep the simulatedto-real clip ratio close to 1:1. For video generation evaluation, we randomly sample 150 clips per test split and generate videos for all sampled clips. Since the compared baselines are primarily trained on nuScenes, we translate the CARLA clips into the nuScenes visual style using learned style-transfer model (details in the supplementary material) for fair evaluation. Evaluation Metrics: We evaluate generated videos along three dimensions: visual quality, physical plausibility, and controllability. (1): Following prior work, we use FID and FVD to measure the realism. (2): For physical plausibility, we adopt WorldModelBench [25], benchmark that can effectively measure the effectiveness of autonomous driving video generation using human preferencealigned VLM-based judges. We report PHY as the average of four WorldModelBench metrics: Mass (objects do not deform irregularly), Impenetrability (objects do not unnaturally pass through each other), Frame-wise Quality (no unappealing frames or low-quality content), and Temporal Quality (no temporally inconsistent scenes and objects). In addition, we report human preference rate (Pref.), computed as the percentage of pairwise comparisons in which method is preferred by human annotators. Detailed questionnaire and settings are provided in the supplementary material. (3): For controllability, we measure how well the generated videos follow the input trajectory conditions. Specifically, we compute the Controllability Error (CtrlErr) between the trajectories extracted PhyGenesis: Physically Consistent Driving Video World Models 11 Fig. 5: Qualitative comparison with different baselines. Our method maintains the best physical consistency and produces the best visual quality. from generated videos and the ground-truth trajectories, defined as the geometric mean of Rotation Error and Translation Error, following prior work [6, 17]. Camera pose sequences are extracted using ViPE [21]. Baseline: We compare our method with three baselines: UniMLVG [4], MagicDriveV2 [9], and DiST-4D [14], evaluating their performance on our dataset. For UniMLVG, MagicDrive-V2, and our framework, the input includes the initial RGB frame, the scene captions, and future layout information. For DiST-4D, it additionally requires the initial-frame depth map alongside the initial RGB frame, providing extra geometric cues. Implementation details of these baselines are provided in the supplementary material. Implementation Details: The training of our Physical Condition Generator conducted on 12Hz data with = 36. Perception-view (PV) features are extracted using ResNet50 [18] initialized from [30] and trained with learning rate of 9105. The main network is trained with learning rate of 9104, and the batch size is set to 256. We set = 2 and for the loss weight Wi,t in Section 3.3, we set λevent = 10 and λagent = 5; an ablation over these hyperparameters is provided in the supplementary material. Our video generation model is initialized from the pre-trained WAN2.1 weights and optimized with AdamW. We adopt two-stage schedule: Stage 1 trains at 224 400 for 2,850 steps with learning rate of 5 105 and global batch size of 480, followed by Stage 2 at 448 800 for 350 steps with learning rate of 1 104 and global batch size of 240. Training is implemented on 48 NVIDIA H20 GPUs. The model generates 33-frame videos at 12 Hz."
        },
        {
            "title": "4.2 Performance of PhyGenesis\nIn this section, we evaluate the effectiveness of PhyGenesis. For nuScenes,\nwe use the ground-truth (x, y) trajectories as the input trajectory condition\nT orig. For CARLA Ego and CARLA ADV, to assess generation under physically-\nviolating trajectory inputs, we construct counterfactual, physics-violating con-",
            "content": "12 J. Zhou et al. Fig. 6: Qualitative comparison on the nuScenes stress test under out-of-distribution (OOD), physics-violating trajectory inputs, with the first-frame condition kept unchanged. Our method outperforms baselines with respect to physical consistency. Table 1: Comparison with baselines under 2D trajectory conditions: nuScenes uses nominal trajectories, while CARLA Ego and CARLA ADV use physics-violating trajectories. We report visual quality (FID/FVD), physical consistency (PHY), human preference (Pref.). PhyGenesis achieves the best results across all datasets. Methods nuScenes CARLA Ego CARLA ADV FID FVD PHY Pref. FID FVD PHY Pref. FID FVD PHY Pref. UniMLVG [4] 17.59 129.69 0.93 MagicDrive-V2 [9] 13.40 91.10 0.92 10.49 46.95 0.86 DiST-4D [14] 10.24 40.41 0.97 PhyGenesis 34.50 260.21 0.55 0.05 32.19 207.64 0.60 0.16 0.13 19.84 197.57 0.39 0.67 11.03 72.48 0.71 0.13 30.32 274.94 0.70 0.06 32.82 222.55 0.66 0.10 16.07 128.88 0.56 0.71 9.28 77.83 0.87 0.19 0.10 0.05 0. ditions following Section 3.3: we keep the pre-collision trajectories unchanged and extrapolate the post-collision motion using each agents pre-collision velocity. For baseline methods, we additionally compute yaw angles from (x, y) to simulate rotation for fair comparison [27]. As shown in Table 1, our framework achieves the best physical scores across all datasets and attains the best visual quality, with the largest gains on the physically challenging CARLA sets, , where physics-violating inputs often cause deformation and penetration in prior methods (Figure 5). To evaluate video generation under out-of-distribution, physically challenging trajectories in real-world scenes, we additionally conduct nuScenes stress test. Specifically, we create physics-violating trajectory conditions in the nuScenes test set by scaling up the ego vehicle speed and retaining only collision cases, while keeping the first-frame condition unchanged. Qualitative and quantitative results in Figure 6 and Figure 7 show that PhyGenesis remains more physically consistent under these corrupted conditions. PhyGenesis: Physically Consistent Driving Video World Models 13 Table 2: Comparison of video generators of different baselines under GT trajectory conditions. We report visual realism (FID/FVD), physical consistency (Phy), and controllability error (CtrlErr); best results are in bold. Methods nuScenes CARLA Ego CARLA ADV FID FVD PHY CtrlErr FID FVD PHY CtrlErr FID FVD PHY CtrlErr 16.63 113.23 0.92 UniMLVG [4] 0.93 MagicDrive-V2 [9] 13.17 88.86 10.48 45.24 DiST-4D [14] 0.84 10.20 31.14 0.97 PhyGenesis 34.03 240.78 0.56 32.92 181.26 0.58 19.94 133.10 0.38 10.98 57.02 0.69 30.06 264.59 0.75 33.62 214.52 0.65 16.12 105.70 0.50 9.07 59.44 0. 1.32 1.26 1.19 0.85 0.35 0.29 0.28 0.25 0.66 0.75 0.57 0.37 Fig. 7: Human preference and Physical score of baseline generations on nuScenes under physics-violating trajectories. Table 3: Performance of the physical condition generator for trajectory rectification. We report the 6-DoF L2 distance to ground truth, comparing w/ and w/o the physical condition generator. Method nuScenes CARLA Ego CARLA ADV w/o Phys. Cond. Generator W/ Phys. Cond. Generator 0.21 0.19 1.78 0.65 1.05 0."
        },
        {
            "title": "4.3 Performance of Physics-enhanced Multi-view Video Generator",
            "content": "In this section, we evaluate the Physics-Enhanced Video Generator. We condition all methods on ground-truth trajectories (i.e., no counterfactual or physicsviolating inputs) and report results on nuScenes, CARLA Ego, and CARLA Adv in Table 2. Although the inputs are physically feasible, prior baselines are trained mostly on nominal logs and rarely see physics-rich interactions (e.g., collisions and off-road events), so they still struggle to render these dynamics, resulting in worse visual quality, physical consistency, and controllability. In contrast, our PE-MVGen is co-trained with physics-rich data, better capturing complex interactions and improving both generation quality and condition following. Fig. 8: Performance of the physical condition generator (visualized in BEV and camera views). The input trajectory on the left penetrates the guardrail, while our condition generator rectifies it, resulting in collision with the guardrail and stop. 14 J. Zhou et al. Fig. 9: Effect of the Physical Condition Generator under physics-violating trajectories: it reduces penetration artifacts between vehicles and the environment. Fig. 10: Effect of heterogeneous co-training: it improves the generation quality in physically challenging frames."
        },
        {
            "title": "4.4 Performance of Physical Condition Generator",
            "content": "In this section, we evaluate Physical Condition Generator. Following Section 4.2, we construct 2D trajectory conditions on nuScenes, CARLA Ego, and CARLA Adv, and report the 6-DoF L2 distance to ground truth before vs. after rectification (on the physical agent and its interaction partner). Table 3 shows consistent error reductions across datasets, and Figure 8 gives qualitative example of trajectory rectification. Gains can be observed on nuScenes since the input provides only 2D (x, y) and the model mainly recovers the missing 4-DoF. In contrast, for physics-violating trajectories in CARLA Ego and CARLA Adv, the model achieves substantial error reduction, demonstrating its effectiveness."
        },
        {
            "title": "4.5 Ablation Study",
            "content": "In this section, we ablate the two key components of PhyGenesis: the Physical Condition Generator and the heterogeneous co-training with physics-rich CARLA data (Mixed Data). Table 4 summarizes the results. Effect of the Physical Condition Generator. Rows (1) and (2) in Table 4 show that the physical condition generator improves both visual quality and indicates co-training our heterogeneous Table 4: Ablation study. Mixed Data dataset, and Phy-Model denotes the integration of our Physical Condition generator. The best results are highlighted in bold. Components nuScenes CARLA Ego CARLA ADV Mixed Data Phy-Model FID FVD PHY Pref. FID FVD PHY Pref. FID FVD PHY Pref. 10.24 40.41 0.97 0.97 10.70 44.43 0.97 10.53 41.06 0.36 11.03 72.48 0.71 0.65 0.26 11.81 116.51 0.71 0.38 12.74 82.39 0.55 0.19 0. 9.28 77.83 0.87 0.85 9.18 89.25 0.84 89.83 9.83 0.57 0.28 0.15 PhyGenesis: Physically Consistent Driving Video World Models 15 physical consistency, with the largest gains on the physically challenging CARLA Ego and CARLA Adv sets. Figure 9 further illustrates it mitigates penetration and deformation artifacts, yielding more physically consistent interactions among vehicles and nearby structures under physics-violating trajectory conditions. Effect of heterogeneous co-training. Rows (1) and (3) in Table 4 shows that incorporating physics-rich CARLA data consistently improves performance on the physically challenging data. On CARLA ADV, heterogeneous training reduces FVD from 89.83 to 77.83 (13.4% relative), along with substantial gain in preference (0.13 to 0.53). Figure 10 shows that training on nominal nuScenes alone often deforms vehicles in challenging interactions, while heterogeneous cotraining produces sharper, more physically coherent dynamics."
        },
        {
            "title": "5 Conclusion",
            "content": "We present PhyGenesis, novel driving world model for physically consistent and high-fidelity multi-view video generation. By explicitly handling trajectory feasibility and physics-enhanced video generation, our approach outperforms existing methods in both visual fidelity and physical consistency, particularly under challenging trajectory conditions. Our framework enables more reliable simulation of safety-critical events such as collisions and off-road behaviors. By better aligning planneror simulator-provided trajectory conditions with physically consistent visual world modeling, PhyGenesis offers practical building block toward simulation-driven evaluation and safety testing in autonomous driving."
        },
        {
            "title": "References",
            "content": "1. Bruce, J., Dennis, M.D., Edwards, A., Parker-Holder, J., Shi, Y., Hughes, E., Lai, M., Mavalankar, A., Steigerwald, R., Apps, C., et al.: Genie: Generative interactive environments. In: Forty-first International Conference on Machine Learning (2024) 2. Caesar, H., Bankiti, V., Lang, A.H., Vora, S., Liong, V.E., Xu, Q., Krishnan, A., Pan, Y., Baldan, G., Beijbom, O.: nuscenes: multimodal dataset for autonomous driving. In: Proceedings of the IEEE/CVF conference on computer vision and pattern recognition. pp. 1162111631 (2020) 3. Chen, Q., Li, F., Xu, S., Lai, Z., Xie, Z., Luo, Y., Jiang, S., Li, H., Chen, L., Wang, B., et al.: Vilta: vlm-in-the-loop adversary for enhancing driving policy robustness. arXiv preprint arXiv:2601.12672 (2026) 4. Chen, R., Wu, Z., Liu, Y., Guo, Y., Ni, J., Xia, H., Xia, S.: Unimlvg: Unified framework for multi-view long video generation with comprehensive control capabilities for autonomous driving. In: Proceedings of the IEEE/CVF International Conference on Computer Vision. pp. 2545325463 (2025) 5. Dosovitskiy, A., Ros, G., Codevilla, F., Lopez, A., Koltun, V.: CARLA: An open urban driving simulator. In: Proceedings of the 1st Annual Conference on Robot Learning. pp. 116 (2017) 6. Duan, H., Yu, H.X., Chen, S., Fei-Fei, L., Wu, J.: Worldscore: unified evaluation benchmark for world generation. In: Proceedings of the IEEE/CVF International Conference on Computer Vision. pp. 2771327724 (2025) J. Zhou et al. 7. Esser, P., Kulal, S., Blattmann, A., Entezari, R., Müller, J., Saini, H., Levi, Y., Lorenz, D., Sauer, A., Boesel, F., et al.: Scaling rectified flow transformers for high-resolution image synthesis. In: Forty-first international conference on machine learning (2024) 8. Fang, Y., Yang, Y., Zhu, X., Zheng, K., Bertasius, G., Szafir, D., Ding, M.: Rebot: Scaling robot learning with real-to-sim-to-real robotic video synthesis. In: 2025 IEEE/RSJ International Conference on Intelligent Robots and Systems (IROS). pp. 1135111358. IEEE (2025) 9. Gao, R., Chen, K., Xiao, B., Hong, L., Li, Z., Xu, Q.: Magicdrive-v2: Highresolution long video generation for autonomous driving with adaptive control. In: Proceedings of the IEEE/CVF International Conference on Computer Vision. pp. 2813528144 (2025) 10. Gao, R., Chen, K., Xie, E., Hong, L., Li, Z., Yeung, D.Y., Xu, Q.: Magicdrive: Street view generation with diverse 3d geometry control. In: International Conference on Learning Representations (ICLR) (2024) 11. Gao, Z., Mu, Y., Chen, C., Duan, J., Luo, P., Lu, Y., Li, S.E.: Enhance sample efficiency and robustness of end-to-end urban autonomous driving via semantic masked world model. IEEE Transactions on Intelligent Transportation Systems 25(10), 1306713079 (2024) 12. Ge, J., Liu, Z., Fan, L., Jiang, Y., Su, J., Li, Y., Zhang, Z., Chen, S.: Unraveling the effects of synthetic data on end-to-end autonomous driving. In: Proceedings of the IEEE/CVF International Conference on Computer Vision. pp. 2885928869 (2025) 13. Gosselin, A., Luo, G.Y., Lara, L., Golemo, F., Nowrouzezahrai, D., Paull, L., Jolicoeur-Martineau, A., Pal, C.: Ctrl-crash: Controllable diffusion for realistic car crashes. arXiv preprint arXiv:2506.00227 (2025) 14. Guo, J., Ding, Y., Chen, X., Chen, S., Li, B., Zou, Y., Lyu, X., Tan, F., Qi, X., Li, Z., et al.: Dist-4d: Disentangled spatiotemporal diffusion with metric depth for 4d driving scene generation. In: Proceedings of the IEEE/CVF International Conference on Computer Vision. pp. 2723127241 (2025) 15. Guo, X., Wu, Z., Xiong, K., Xu, Z., Zhou, L., Xu, G., Xu, S., Sun, H., Wang, B., Chen, G., et al.: Genesis: Multimodal driving scene generation with spatiotemporal and cross-modal consistency. arXiv preprint arXiv:2506.07497 (2025) 16. Guo, Z., Zhou, Y., Gou, C.: Drivinggen: Efficient safety-critical driving video generation with latent diffusion models. In: 2024 IEEE International Conference on Multimedia and Expo (ICME). pp. 16. IEEE (2024) 17. He, H., Xu, Y., Guo, Y., Wetzstein, G., Dai, B., Li, H., Yang, C.: Cameractrl: Enabling camera control for text-to-video generation. arXiv preprint arXiv:2404.02101 (2024) 18. He, K., Zhang, X., Ren, S., Sun, J.: Deep residual learning for image recognition. In: Proceedings of the IEEE conference on computer vision and pattern recognition. pp. 770778 (2016) 19. Hu, A., Corrado, G., Griffiths, N., Murez, Z., Gurau, C., Yeo, H., Kendall, A., Cipolla, R., Shotton, J.: Model-based imitation learning for urban driving. Advances in Neural Information Processing Systems 35, 2070320716 (2022) 20. Hu, A., Russell, L., Yeo, H., Murez, Z., Fedoseev, G., Kendall, A., Shotton, J., Corrado, G.: Gaia-1: generative world model for autonomous driving. arXiv preprint arXiv:2309.17080 (2023) 21. Huang, J., Zhou, Q., Rabeti, H., Korovko, A., Ling, H., Ren, X., Shen, T., Gao, J., Slepichev, D., Lin, C.H., et al.: Vipe: Video pose engine for 3d geometric perception. arXiv preprint arXiv:2508.10934 (2025) PhyGenesis: Physically Consistent Driving Video World Models 17 22. Jia, X., Yang, Z., Li, Q., Zhang, Z., Yan, J.: Bench2drive: Towards multi-ability benchmarking of closed-loop end-to-end autonomous driving. Advances in Neural Information Processing Systems 37, 819844 (2024) 23. Li, B., Guo, J., Liu, H., Zou, Y., Ding, Y., Chen, X., Zhu, H., Tan, F., Zhang, C., Wang, T., Zhou, S., Zhang, L., Qi, X., Zhao, H., Yang, M., Zeng, W., Jin, X.: Uniscene: Unified occupancy-centric driving scene generation. In: IEEE/CVF Conference on Computer Vision and Pattern Recognition, CVPR 2025, Nashville, TN, USA, June 11-15, 2025. pp. 1197111981. Computer Vision Foundation / IEEE (2025) 24. Li, C., Zhou, K., Liu, T., Wang, Y., Zhuang, M., Gao, H., Jin, B., Zhao, H.: AVD2: accident video diffusion for accident video description. In: IEEE International Conference on Robotics and Automation, ICRA 2025, Atlanta, GA, USA, May 19-23, 2025. pp. 1328913296. IEEE (2025) 25. Li, D., Fang, Y., Chen, Y., Yang, S., Cao, S., Wong, J., Luo, M., Wang, X., Yin, H., Gonzalez, J.E., et al.: Worldmodelbench: Judging video generation models as world models. arXiv preprint arXiv:2502.20694 (2025) 26. Li, Y., Xiong, K., Guo, X., Li, F., Yan, S., Xu, G., Zhou, L., Chen, L., Sun, H., Wang, B., et al.: Recogdrive: reinforced cognitive framework for end-to-end autonomous driving. arXiv preprint arXiv:2506.08052 (2025) 27. Liao, B., Chen, S., Yin, H., Jiang, B., Wang, C., Yan, S., Zhang, X., Li, X., Zhang, Y., Zhang, Q., et al.: Diffusiondrive: Truncated diffusion model for end-to-end autonomous driving. In: Proceedings of the Computer Vision and Pattern Recognition Conference. pp. 1203712047 (2025) 28. NVIDIA: World simulation with video foundation models for physical AI. arXiv preprint arXiv:2511.00062 (2025) 29. Shi, C., Shi, S., Sheng, K., Zhang, B., Jiang, L.: Drivex: Omni scene modeling for learning generalizable world knowledge in autonomous driving. In: Proceedings of the IEEE/CVF International Conference on Computer Vision. pp. 2859928609 (2025) 30. Sun, W., Lin, X., Shi, Y., Zhang, C., Wu, H., Zheng, S.: Sparsedrive: End-to-end autonomous driving via sparse scene representation. In: 2025 IEEE International Conference on Robotics and Automation (ICRA). pp. 87958801. IEEE (2025) 31. Swerdlow, A., Xu, R., Zhou, B.: Street-view image generation from birds-eye view layout. IEEE Robotics Autom. Lett. 9(4), 35783585 (2024) 32. Team, Q.: Qwen2.5-vl (January 2025), https://qwenlm.github.io/blog/qwen2. 5-vl/ 33. Wan, T., Wang, A., Ai, B., Wen, B., Mao, C., Xie, C.W., Chen, D., Yu, F., Zhao, H., Yang, J., et al.: Wan: Open and advanced large-scale video generative models. arXiv preprint arXiv:2503.20314 (2025) 34. Wang, X., Zhu, Z., Huang, G., Chen, X., Zhu, J., Lu, J.: Drivedreamer: Towards real-world-drive world models for autonomous driving. In: European conference on computer vision. pp. 5572. Springer (2024) 35. Wen, Y., Zhao, Y., Liu, Y., Jia, F., Wang, Y., Luo, C., Zhang, C., Wang, T., Sun, X., Zhang, X.: Panacea: Panoramic and controllable video generation for autonomous driving. In: Proceedings of the IEEE/CVF Conference on Computer Vision and Pattern Recognition. pp. 69026912 (2024) 36. Xia, T., Li, Y., Zhou, L., Yao, J., Xiong, K., Sun, H., Wang, B., Ma, K., Chen, G., Ye, H., et al.: Drivelaw: Unifying planning and video generation in latent driving world. arXiv preprint arXiv:2512.23421 (2025) 18 J. Zhou et al. 37. Xu, Z., Li, B., Gao, H.a., Gao, M., Chen, Y., Liu, M., Yan, C., Zhao, H., Feng, S., Zhao, H.: Challenger: Affordable adversarial driving video generation. arXiv preprint arXiv:2505.15880 (2025) 38. Yan, T., Wu, D., Han, W., Jiang, J., Zhou, X., Zhan, K., Xu, C.z., Shen, J.: Drivingsphere: Building high-fidelity 4d world for closed-loop simulation. In: Proceedings of the Computer Vision and Pattern Recognition Conference. pp. 2753127541 (2025) 39. Yang, J., Chitta, K., Gao, S., Chen, L., Shao, Y., Jia, X., Li, H., Geiger, A., Yue, X., Chen, L.: Resim: Reliable world simulation for autonomous driving. arXiv preprint arXiv:2506.09981 (2025) 40. Yang, K., Ma, E., Peng, J., Guo, Q., Lin, D., Yu, K.: Bevcontrol: Accurately controlling street-view elements with multi-perspective consistency via bev sketch layout. arXiv preprint arXiv:2308.01661 (2023) 41. Yang, L., Kang, B., Huang, Z., Zhao, Z., Xu, X., Feng, J., Zhao, H.: Depth anything v2. Advances in Neural Information Processing Systems 37, 2187521911 (2024) 42. Yang, X., Wen, L., Wei, T., Ma, Y., Mei, J., Li, X., Lei, W., Fu, D., Cai, P., Dou, M., et al.: Drivearena: closed-loop generative simulation platform for autonomous driving. In: Proceedings of the IEEE/CVF International Conference on Computer Vision. pp. 2693326943 (2025) 43. Zeng, K., Wu, Z., Xiong, K., Wei, X., Guo, X., Zhu, Z., Ho, K., Zhou, L., Zeng, B., Lu, M., et al.: Rethinking driving world model as synthetic data generator for perception tasks. arXiv preprint arXiv:2510.19195 (2025) 44. Zeng, S., Chang, X., Xie, M., Liu, X., Bai, Y., Pan, Z., Xu, M., Wei, X.: Futuresightdrive: Thinking visually with spatio-temporal cot for autonomous driving. In: The Thirty-ninth Annual Conference on Neural Information Processing Systems (2025) 45. Zhao, G., Wang, X., Zhu, Z., Chen, X., Huang, G., Bao, X., Wang, X.: Drivedreamer-2: Llm-enhanced world models for diverse driving video generation. In: Proceedings of the AAAI Conference on Artificial Intelligence. vol. 39, pp. 1041210420 (2025) 46. Zhou, J., Lyu, L., Tian, Z., Zhuo, C., Li, Y.: Safemvdrive: Multi-view safety-critical driving video synthesis in the real world domain. arXiv preprint arXiv:2505.17727 (2025) 47. Zhu, Z., Wu, Z., Zhu, Z., Zhou, L., Sun, H., Wan, B., Ma, K., Chen, G., Ye, H., Xie, J., et al.: Worldsplat: Gaussian-centric feed-forward 4d scene generation for autonomous driving. arXiv preprint arXiv:2509.23402 (2025) PhyGenesis: Physically Consistent Driving Video World Models"
        },
        {
            "title": "A User Study Setting",
            "content": "Fig. 11: The questionnaire used to evaluate the visual quality of videos generated by different baselines in the user study. In our experiments, participants are shown videos generated by different baselines under the same conditions and are asked to select the one with the highest visual quality. In addition to selecting one of the candidate videos, participants may also choose an uncertain option. selected video is assigned 1 point, while for an uncertain response, the score is distributed equally among all compared 20 J. Zhou et al. videos, with each video receiving 1/N point, where is the number of videos in the comparison. The final score is computed as the total points received divided by the total number of comparisons. The questionnaire used in our study is shown in Figure 11. The user studies reported in Table 1, Figure 7, and Table 4 of the main paper are conducted separately. For each study, we randomly sample generated videos from five scenes in the corresponding evaluation dataset for comparison. Each human preference score is based on 150 responses collected from 30 participants. In total, we collect 1,050 responses across all user studies."
        },
        {
            "title": "B Style Transfer Model Used for Video Generation",
            "content": "Since the compared baselines are primarily trained on nuScenes, we introduce style transfer model to ensure fair comparison. Our transfer model is built upon Wan2.1-Fun-V1.1-1.3B-Control [33] and follows the same rectified-flow video generation framework. Specifically, we adapt the generation model to the style transfer setting by conditioning it on per-frame depth information and detailed textual descriptions, so that CARLA clips can be translated into the nuScenes visual style. After stylizing the full CARLA videos into the nuScenes domain, we can provide all compared video generation methods with nuScenes-style initial frames on the CARLA benchmark, and also obtain stylized videos to be the groundtruth for computing FID and FVD. The architecture of the transfer model is shown in Figure 12. Specifically, we use Depth Anything V2 (DAV2) [41] to extract per-frame depth maps from the input video, and, similar to the main model, concatenate the resulting depth latents with noisy video latents as generation conditions, without using the initial frame as conditioning input. In addition, we use Qwen2.5-VL [32] to produce detailed description for the entire video, as the semantic content of the video is already fixed. The prompt used for generating video-level captions is shown in Figure 13. Importantly, the transfer model is trained entirely on nuScenes data, rather than on heterogeneous mixed-domain data. This design encourages the model to learn the appearance characteristics of the nuScenes domain more faithfully. Since the initial frame is not used as conditioning input, the models generation inherently reflects the nuScenes style rather than the specific appearance of the input video. During inference, the trained transfer model is applied to CARLA videos to translate them into the nuScenes style. Training Objective. Following the rectified-flow formulation used in the main paper, let z1 denote the clean target video latent, let z0 (0, I) be random noise latent, and let [0, 1] be the sampled timestep. The noisy latent is constructed as zt = tz1 + (1 t)z0. (10) PhyGenesis: Physically Consistent Driving Video World Models 21 Fig. 12: Architecture of the style transfer model used to translate CARLA videos into the nuScenes visual style for fair comparison. The transfer model is trained with the same flow-matching objective, conditioned on the video-level caption ctext, and the per-frame depth condition cdepth: Ltransfer = Ez0,z1,t uθ(zt, t, ctext, cdepth) (z1 z0)2 2 . (11)"
        },
        {
            "title": "C Implementation Details of Different Baselines",
            "content": "In this paper, we compare our method with three baselines, all evaluated using their official pretrained weights. For all methods, we generate videos consisting of 33 frames. Our method, MagicDriveV2 [9], and DiST-4D [14] generate the entire video in single pass. In contrast, UniMLVG [4] can generate at most 19 frames at time. Therefore, we follow its official autoregressive inference code 22 J. Zhou et al. Fig. 13: Prompt used in the VLM for generating detailed video-level captions. to produce 33-frame video in two stages: the first pass generates frames 114, and the second pass generates frames 1433, using the intermediate frame as the conditioning frame for the second stage. Our method generates videos at resolution of 448 800. MagicDriveV2 and DiST-4D generate videos at 424 800, while UniMLVG generates videos at 256 448, since it is trained only at this resolution. Our method, MagicDriveV2, and UniMLVG all use the initial RGB frame as the generation condition. DiST-4D additionally uses the depth map of the initial frame as an extra condition, which we obtain using its official preprocessing pipeline. For the CARLA stylized domain, we apply one-epoch adaptation to the Physical Condition Generator on stylized initial frames from the CARLA training set, while keeping the Physics-enhanced Multi-view Video Generator unchanged. Physical-Challenging Scenario Construction in"
        },
        {
            "title": "CARLA Ego and CARLA Adv",
            "content": "We construct physically challenging scenarios in CARLA [5] based on the Bench2Drive [22] routing setup. Each rollout starts from valid predefined route while preserving the original map layout, traffic participants, weather, and background behaviors. On top of this standard setup, we perturb the behavior of one designated vehicle to induce physically challenging events. The perturbation is parameterized by two variables: lateral route offset and target speed. Specifically, the target speed is sampled from predefined values between 0 and 30 m/s, with uniform random perturbations within the intervals around each value, and the lateral offset is sampled from predefined values between -200 and 200 meters, with uniform random perturbations within the intervals around each value. At scene initialization, we further choose one of three perturbation modes with PhyGenesis: Physically Consistent Driving Video World Models 23 equal probability: (i) zero lateral offset with randomized target speed, (ii) fixed target speed of 10 m/s with randomized lateral offset, and (iii) both target speed and lateral offset randomized. This design yields broad spectrum of behaviors ranging from mild deviations to aggressive maneuvers. For CARLA Ego, the perturbed vehicle is the ego vehicle itself. The ego vehicle first follows the default autopilot for warm-up period of 24 steps. Since our simulator runs at 12 Hz, this corresponds to 2 seconds. After the warmup, we replace the nominal route with smoothed and supersampled route, and then apply cosine-smoothed lateral offset to the future route points so that the vehicle gradually transitions from its current route to the perturbed one. The ego vehicle is then controlled to track this modified route under the sampled target speed. For CARLA Adv, we instead perturb nearby non-ego vehicle. We first spawn an adversarial vehicle near the ego vehicle by sampling valid waypoint within local neighborhood of the ego route, including forward, backward, and adjacent-lane candidates within approximately 15 meters. The adversarial vehicle also follows the default controller for the same 24-step warmup period. Afterward, we transform the ego route into the adversarial vehicles local initialization frame and apply the same perturbation mechanism. As result, the physically challenging behavior is centered on nearby non-ego agent rather than the ego vehicle. During rollout, we monitor collisions and off-road departures for the perturbed vehicle. Collisions are detected using CARLA collision sensors, and the collided object category is recorded, including vehicles, pedestrians, parked vehicles, traffic objects, and static objects. Off-road events are detected by querying the local lane type and checking whether the vehicle enters sidewalk or shoulder regions. Once an event is triggered, we continue collecting data for 48 additional frames, corresponding to 4 seconds at 12 Hz, and then terminate the rollout. We also terminate the rollout if no event is observed within 120 post-warm-up steps, i.e., 10 seconds. In this way, each collected sequence contains the preevent context, the event itself, and its short-term consequence. The resulting dataset therefore consists of route-grounded but physically challenging trajectories. CARLA Ego emphasizes failures and abrupt maneuvers induced on the ego vehicle, while CARLA Adv emphasizes interactions caused by nearby perturbed non-ego vehicle. Weighting Design and Ablation Study of λevent and λagent In the Physical Condition Generator optimization, Wi,t is defined using two scalar hyperparameters to prioritize physically important samples. The temporal weight λevent reweights the loss along the time dimension by assigning larger weights to timesteps near critical events such as collision or off-road. For each event timestep te, we define forward window [se, ee], where se = max(0, te 1) and ee = min(T 1, te +10), with denoting the prediction horizon. Within this window, the temporal weight is initialized at λevent and exponentially decays to 24 1: J. Zhou et al. we(t) = λevent exp (cid:18) log(1/λevent) ee se (cid:19) (t se) , [se, ee]. If multiple event windows overlap, we take the maximum weight at each timestep:"
        },
        {
            "title": "W event\nt",
            "content": "= max we(t), and set event = 1 for timesteps outside all event windows. This design makes the supervision strongest near the onset of physical event while preserving standard supervision on the remaining horizon. The agent weight λagent further reweights the loss along the agent dimension by assigning larger multiplicative factor to the agents that are most relevant to the physical event. The selection is determined based on the event annotations in the dataset. When the event corresponds to collision with static object, such as fence or lamp post, only the ego vehicle (or the Adv vehicle) is emphasized. When the event corresponds to collision with dynamic participant, such as another vehicle or pedestrian, we additionally emphasize the agent that is nearest to the ego vehicle (or the Adv vehicle) at the collision timestep. In this way, the optimization focuses on the participants that are most directly related to the event, which helps better model the trajectory behavior around the collision moment. The ablation study presented in Tables 5 and 6 indicates that different values of λevent and λagent have limited effect on performance. This suggests that the model is largely robust to these hyperparameters while the weighting mechanism still provides focused supervision around critical events and agents. Table 5: Ablation study on λevent. Configuration nuScenes CARLA Ego CARLA ADV baseline λevent = 1 λevent = 5 λevent = 10 0.21 0.17 0.16 0.16 1.78 0.56 0.58 0. 1.05 0.69 0.76 0.77 PhyGenesis: Physically Consistent Driving Video World Models 25 Table 6: Ablation study on λagent. Configuration nuScenes CARLA Ego CARLA ADV baseline λagent = 1 λagent = 10 λagent = 0.21 0.13 0.16 0.16 1.78 0.53 0.58 0.62 1.05 0.70 0.76 0."
        }
    ],
    "affiliations": [
        "Shenzhen Loop Area Institute",
        "The Hong Kong Polytechnic University",
        "Xiaomi EV",
        "Zhejiang University"
    ]
}