[
    {
        "header": "Abstract",
        "images": [
            {
                "img": "https://arxiv.org/html/2511.04583/x1.png",
                "caption": "Figure 1:Jr. AI Scientist Workflow.We provide the baseline paper, its LaTeX source files, and the associated codebase. By effectively utilizing these resources across all phases, the system significantly improves the quality of the generated paper.",
                "position": 121
            },
            {
                "img": "https://arxiv.org/html/2511.04583/x2.png",
                "caption": "Figure 2:Jr. AI Scientist Workflow for the Experiment Phase.The workflow consists of three stages. Through bug management and performance tracking, our system passes the most promising experimental nodes to the next stage.",
                "position": 264
            },
            {
                "img": "https://arxiv.org/html/2511.04583/x3.png",
                "caption": "Figure 3:Jr. AI Scientist Workflow for the Writing Phase.The Writing process consists of three steps: Draft Writing, Reflection, and Adjustment.",
                "position": 362
            },
            {
                "img": "https://arxiv.org/html/2511.04583/x4.png",
                "caption": "Figure 4:An example of a generated paper. Our Jr. AI Scientist can generate full-length research papers with appendices.",
                "position": 520
            }
        ]
    },
    {
        "header": "Appendix",
        "images": []
    }
]