[
    {
        "header": "Abstract",
        "images": []
    },
    {
        "header": "1Introduction",
        "images": [
            {
                "img": "https://arxiv.org/html/2601.19375/x1.png",
                "caption": "Figure 1:Selective Steering pipeline.At each layerkk, we compute projections of positive (red) and negative (blue) class means onto the selected feature direction (red/blueboxes).\nSteering is applied only at layers where projections have opposite signs (layersk−2k-2andk+1k+1), using norm-preserving rotation.\nLayers with same-sign projections (layerk−1k-1) remain unchanged.",
                "position": 250
            }
        ]
    },
    {
        "header": "2Background",
        "images": []
    },
    {
        "header": "3Methodology",
        "images": [
            {
                "img": "https://arxiv.org/html/2601.19375/x2.png",
                "caption": "(a)",
                "position": 423
            },
            {
                "img": "https://arxiv.org/html/2601.19375/x2.png",
                "caption": "(a)",
                "position": 426
            },
            {
                "img": "https://arxiv.org/html/2601.19375/x3.png",
                "caption": "(b)",
                "position": 432
            }
        ]
    },
    {
        "header": "4Experiments",
        "images": [
            {
                "img": "https://arxiv.org/html/2601.19375/x4.png",
                "caption": "Figure 3:Perplexity measurements across the full steering circle (0°-360°, 10° intervals) forSAS, AAS,andSelective Steering (SS). Each subplot shows one model’s perplexity profile, with the baseline (no steering) shown as a dashed circle.Red starsindicate angles where perplexity exceeds the threshold of 2.0, signaling generation instability or collapse.ActAddandDirAblare excluded as they provide only single-point steering rather than continuous angular control.",
                "position": 642
            }
        ]
    },
    {
        "header": "5Conclusion",
        "images": []
    },
    {
        "header": "6Limitations",
        "images": []
    },
    {
        "header": "Ethics Statement",
        "images": []
    },
    {
        "header": "References",
        "images": []
    },
    {
        "header": "Appendix ARelated Work",
        "images": []
    },
    {
        "header": "Appendix BDetailed Methodology",
        "images": []
    },
    {
        "header": "Appendix CDetailed Evaluation Metrics",
        "images": []
    },
    {
        "header": "Appendix DAdditional Results",
        "images": []
    },
    {
        "header": "Appendix EAblation Studies",
        "images": []
    },
    {
        "header": "Appendix FComputational Requirements",
        "images": []
    },
    {
        "header": "Appendix GQualitative Analysis",
        "images": [
            {
                "img": "https://arxiv.org/html/2601.19375/x5.png",
                "caption": "Figure 4:Controllability of Selective Steering across rotation angles.Each subplot shows attack success rates (ASR) for four evaluators as a function of steering angleθ∈[0​°,360​°)\\theta\\in[0°,360°). Radial distance indicates ASR magnitude (0.0–1.0). Most models exhibit a clear peak region (typically 180°–270°) where compliance is maximized, demonstrating smooth behavioral control.Note:Gemma family models show bimodal peaks, suggesting the chosen feature direction may not be optimal for this architecture, highlighting the importance of feature extraction quality (see Section6).",
                "position": 3497
            },
            {
                "img": "https://arxiv.org/html/2601.19375/x6.png",
                "caption": "(a)",
                "position": 3675
            },
            {
                "img": "https://arxiv.org/html/2601.19375/x6.png",
                "caption": "(a)",
                "position": 3678
            },
            {
                "img": "https://arxiv.org/html/2601.19375/x7.png",
                "caption": "(b)",
                "position": 3684
            },
            {
                "img": "https://arxiv.org/html/2601.19375/x8.png",
                "caption": "(a)",
                "position": 3693
            },
            {
                "img": "https://arxiv.org/html/2601.19375/x8.png",
                "caption": "(a)",
                "position": 3696
            },
            {
                "img": "https://arxiv.org/html/2601.19375/x9.png",
                "caption": "(b)",
                "position": 3702
            },
            {
                "img": "https://arxiv.org/html/2601.19375/x10.png",
                "caption": "(a)",
                "position": 3711
            },
            {
                "img": "https://arxiv.org/html/2601.19375/x10.png",
                "caption": "(a)",
                "position": 3714
            },
            {
                "img": "https://arxiv.org/html/2601.19375/x11.png",
                "caption": "(b)",
                "position": 3720
            },
            {
                "img": "https://arxiv.org/html/2601.19375/x12.png",
                "caption": "(a)",
                "position": 3729
            },
            {
                "img": "https://arxiv.org/html/2601.19375/x12.png",
                "caption": "(a)",
                "position": 3732
            },
            {
                "img": "https://arxiv.org/html/2601.19375/x13.png",
                "caption": "(b)",
                "position": 3738
            },
            {
                "img": "https://arxiv.org/html/2601.19375/x14.png",
                "caption": "(a)",
                "position": 3747
            },
            {
                "img": "https://arxiv.org/html/2601.19375/x14.png",
                "caption": "(a)",
                "position": 3750
            },
            {
                "img": "https://arxiv.org/html/2601.19375/x15.png",
                "caption": "(b)",
                "position": 3756
            },
            {
                "img": "https://arxiv.org/html/2601.19375/x16.png",
                "caption": "(a)",
                "position": 3765
            },
            {
                "img": "https://arxiv.org/html/2601.19375/x16.png",
                "caption": "(a)",
                "position": 3768
            },
            {
                "img": "https://arxiv.org/html/2601.19375/x17.png",
                "caption": "(b)",
                "position": 3774
            },
            {
                "img": "https://arxiv.org/html/2601.19375/x18.png",
                "caption": "(a)",
                "position": 3783
            },
            {
                "img": "https://arxiv.org/html/2601.19375/x18.png",
                "caption": "(a)",
                "position": 3786
            },
            {
                "img": "https://arxiv.org/html/2601.19375/x19.png",
                "caption": "(b)",
                "position": 3792
            },
            {
                "img": "https://arxiv.org/html/2601.19375/x20.png",
                "caption": "(a)",
                "position": 3801
            },
            {
                "img": "https://arxiv.org/html/2601.19375/x20.png",
                "caption": "(a)",
                "position": 3804
            },
            {
                "img": "https://arxiv.org/html/2601.19375/x21.png",
                "caption": "(b)",
                "position": 3810
            }
        ]
    },
    {
        "header": "Appendix HLayer-Wise Heterogeneity Across Model Families",
        "images": []
    }
]