[
    {
        "header": "Abstract",
        "images": [
            {
                "img": "https://arxiv.org/html/2605.22144/2605.22144v1/figures_paper/teaser_final.png",
                "caption": "Figure 1:Fromone sentenceto afull short drama: we show four highlight abilities by our multi-agent pipeline in structured story synthesis, hook design, spatial consistency, and product-level quality.",
                "position": 269
            }
        ]
    },
    {
        "header": "1Introduction",
        "images": []
    },
    {
        "header": "2Personalized Short-Form Drama Generation",
        "images": [
            {
                "img": "https://arxiv.org/html/2605.22144/2605.22144v1/figures_paper/pipeline_final_light.png",
                "caption": "Figure 2:Overview of our personalized short-form drama generation pipeline four stages.\nGiven a single-sentence input, the system generates structured story and clip scripts through retrieval and multi-agent debate (A), expands into visual assets and paired first-frame/video prompts with prompt review (B), produces 3D-anchored keyframe-to-video clips with frame and video review loops (C), and assembles the final drama with scene transition planning and adaptive BGM mixing (D).",
                "position": 327
            },
            {
                "img": "https://arxiv.org/html/2605.22144/2605.22144v1/figures_paper/3D_consistent_final.png",
                "caption": "Figure 3:Consistent first-frame synthesis via 3D scene grounding.\nWe reconstruct a scene-level 3D world from a panorama, register generated clips and the human mesh into the shared coordinate system, and synthesize the next first-frame through geometry-semantic-aware camera selection, character-conditioned generation, and frame quality analysis and repair.",
                "position": 408
            }
        ]
    },
    {
        "header": "3Experiments",
        "images": [
            {
                "img": "https://arxiv.org/html/2605.22144/2605.22144v1/figures_paper/qualitative1_final.png",
                "caption": "Figure 4:Qualitative examples.\nTop: comparison between our generated results and baselines on cross-clip visual continuity and drama pacing.\nBottom: visualization of our complete drama generation process, including atom retrieval, story structurization, scene/clip script synthesis, visual asset generation, prompt synthesis, and cross-clip 3D-consistent generation.",
                "position": 519
            },
            {
                "img": "https://arxiv.org/html/2605.22144/2605.22144v1/figures_paper/qualitative2_final_light.png",
                "caption": "",
                "position": 523
            },
            {
                "img": "https://arxiv.org/html/2605.22144/2605.22144v1/x1.png",
                "caption": "Table 1:Quantitative evaluations.Top-left:comparison on standard video and story-visualization benchmarks.Bottom-left:comparison on our proposed short-drama-Bench metrics, covering narrative hooks, narrative flow, cross-clip continuity, and audio-transition quality.Right:human rating on the same short-drama criteria, averaged over 20 annotators across the benchmark.\nThe radar plot normalizes each axis by the score of our method to show superior performance over baselines.†denotes closed-source commercial products evaluated via public interface.",
                "position": 542
            }
        ]
    },
    {
        "header": "4Related Work",
        "images": []
    },
    {
        "header": "5Conclusion",
        "images": []
    },
    {
        "header": "References",
        "images": []
    },
    {
        "header": "Appendix Overview",
        "images": []
    },
    {
        "header": "Appendix ABroader Impacts",
        "images": []
    },
    {
        "header": "Appendix BRelated Work",
        "images": []
    },
    {
        "header": "Appendix CDetails of the Multi-Agent Debating-based Story Generation Framework",
        "images": [
            {
                "img": "https://arxiv.org/html/2605.22144/2605.22144v1/x2.png",
                "caption": "Figure 5:The Multi-Agent Debating-based Story Generation Framework.",
                "position": 1907
            }
        ]
    },
    {
        "header": "Appendix DDetails of Diverse Transition Clips and BGM Planning & Mixing",
        "images": [
            {
                "img": "https://arxiv.org/html/2605.22144/2605.22144v1/x3.png",
                "caption": "Figure 6:Our Diverse Transition Clips and BGM Planning & Mixing",
                "position": 1935
            }
        ]
    },
    {
        "header": "Appendix EMulti-Character 3D-Consistent First-Frame Generation.",
        "images": []
    },
    {
        "header": "Appendix FHuman Rating Details",
        "images": []
    },
    {
        "header": "Appendix GDetailed Experiment Settings",
        "images": []
    },
    {
        "header": "Appendix HTime and Cost Analysis",
        "images": []
    },
    {
        "header": "Appendix ILimitations",
        "images": []
    },
    {
        "header": "Appendix JMulti-Stage Review Metrics and Judge Models",
        "images": []
    },
    {
        "header": "Appendix KShort-Drama-Bench Prompts and Generated Videos",
        "images": [
            {
                "img": "https://arxiv.org/html/2605.22144/2605.22144v1/x4.png",
                "caption": "Figure 7:Gallery One Of Generated Videos",
                "position": 3545
            },
            {
                "img": "https://arxiv.org/html/2605.22144/2605.22144v1/x5.png",
                "caption": "Figure 8:Gallery Two Of Generated Videos",
                "position": 3548
            }
        ]
    },
    {
        "header": "Appendix LScript Library and BGM Library Details",
        "images": [
            {
                "img": "https://arxiv.org/html/2605.22144/2605.22144v1/x6.png",
                "caption": "Figure 9:Our BGM Datasets",
                "position": 3565
            }
        ]
    },
    {
        "header": "Appendix MPrompt Templates for Each Stage",
        "images": []
    },
    {
        "header": "Instructions for reporting errors",
        "images": []
    }
]