[
    {
        "header": "Abstract",
        "images": []
    },
    {
        "header": "1Introduction",
        "images": [
            {
                "img": "https://arxiv.org/html/2606.30634/2606.30634v1/figures/10b-train-loss-redacted.png",
                "caption": "Figure 1:Training loss on a 10B MoE model trained for 200B FineWeb-Edu tokens.\nBoth asynchronous runs remain stable throughout training, with Async PP + Error Feedback closing the final gap to the synchronous baseline entirely.",
                "position": 335
            },
            {
                "img": "https://arxiv.org/html/2606.30634/2606.30634v1/figures/360M_optimizers_improved.png",
                "caption": "Figure 2:Validation loss of synchronous and one-step delayed optimizers on the 360M model.\nFor most optimizers, Error Feedback cuts the sync-async gap by more than half compared to standard delayed training and outperforms the synchronous-start baseline.",
                "position": 382
            }
        ]
    },
    {
        "header": "2One-Step Delayed Optimization",
        "images": [
            {
                "img": "https://arxiv.org/html/2606.30634/2606.30634v1/figures/fig3.png",
                "caption": "Figure 3:Synchronous and delayed AdamW and Muon training on the 360M model.\nAdamW degrades substantially under one-step delay, even with a synchronous start, whereas Muon achieves a much smaller final sync-async gap.",
                "position": 488
            },
            {
                "img": "https://arxiv.org/html/2606.30634/2606.30634v1/figures/beta_part1.png",
                "caption": "Figure 4:Final loss gap between synchronous and asynchronous training as a function of the momentum decay for various optimizers.Note that we exclude certain high-momentum configurations in which the synchronous baseline itself diverges due to instability.",
                "position": 695
            },
            {
                "img": "https://arxiv.org/html/2606.30634/2606.30634v1/figures/beta_part1.png",
                "caption": "",
                "position": 698
            },
            {
                "img": "https://arxiv.org/html/2606.30634/2606.30634v1/figures/beta_part2.png",
                "caption": "",
                "position": 702
            }
        ]
    },
    {
        "header": "3Staleness Mitigation",
        "images": []
    },
    {
        "header": "4Theoretical analysis",
        "images": []
    },
    {
        "header": "5Large Scale Experiments",
        "images": [
            {
                "img": "https://arxiv.org/html/2606.30634/2606.30634v1/figures/d_figure_redacted.png",
                "caption": "Figure 5:Validation loss of the 2B MoE model across training horizons.\nThe synchronous and asynchronous scaling curves remain nearly parallel from5050B to200200B tokens, indicating no growth of the sync-async gap with longer training; Error Feedback consistently reduces the remaining gap.",
                "position": 1204
            },
            {
                "img": "https://arxiv.org/html/2606.30634/2606.30634v1/figures/arxiv_plots/pipedream_comparison.png",
                "caption": "Figure 6:Comparison of synchronous training, PipeDream-2BWwith constant one-step delay, and the original PipeDream schedule with variable delay on the 135M model.\nHerePPdenotes the number of pipeline stages in the original PipeDream schedule; PipeDream-2BWhas a constant one-step delay independent ofPP.\nAsPPincreases, original PipeDream progressively degrades relative to the corresponding PipeDream-2BWruns.\nThis illustrates that variable delay remains a major source of degradation at larger pipeline depths.",
                "position": 1229
            }
        ]
    },
    {
        "header": "6Comparison with PipeDream",
        "images": []
    },
    {
        "header": "7Related work",
        "images": []
    },
    {
        "header": "8Discussion and Limitations",
        "images": []
    },
    {
        "header": "Acknowledgements",
        "images": []
    },
    {
        "header": "Impact Statement",
        "images": []
    },
    {
        "header": "References",
        "images": []
    },
    {
        "header": "Appendix AHyperparameter Sensitivity Results and Other Additional Experiments",
        "images": [
            {
                "img": "https://arxiv.org/html/2606.30634/2606.30634v1/figures/arxiv_plots/sweep_lr_absolute_trim2.png",
                "caption": "Figure 7:Effect of peak learning rate on synchronous and one-step delayed training on the 135M model.\nBars show final validation loss, and annotations indicate the sync-async gap.\nLower learning rates mildly reduce the gap for robust optimizers, while large learning rates can substantially worsen delayed training for AdamW.",
                "position": 2414
            },
            {
                "img": "https://arxiv.org/html/2606.30634/2606.30634v1/figures/arxiv_plots/sweep_wd_absolute_trim2.png",
                "caption": "Figure 8:Effect of weight decay on synchronous and one-step delayed training on the 135M model.\nModerate values have limited effect for robust optimizers, while extreme values can substantially worsen delayed training.\nAdamW is especially sensitive to small weight decay in this sweep.",
                "position": 2429
            },
            {
                "img": "https://arxiv.org/html/2606.30634/2606.30634v1/figures/arxiv_plots/sweep_warmup_absolute.png",
                "caption": "Figure 9:Effect of learning-rate warmup length on one-step delayed training on the 135M model.\nThe delay is enabled from the first step in all runs.\nLonger warmup mildly reduces the sync-async gap, with the largest visible effect for AdamW.",
                "position": 2444
            },
            {
                "img": "https://arxiv.org/html/2606.30634/2606.30634v1/figures/arxiv_plots/sweep_gc_absolute.png",
                "caption": "Figure 10:Effect of gradient clipping threshold on synchronous and one-step delayed training on the 135M model.\nThe sync-async gap is largely insensitive to the clipping threshold for the robust optimizers tested here.",
                "position": 2456
            },
            {
                "img": "https://arxiv.org/html/2606.30634/2606.30634v1/figures/arxiv_plots/sweep_scheduler.png",
                "caption": "Figure 11:Effect of learning-rate scheduler on synchronous and one-step delayed training on the 135M model.\nThe gap is similar across the tested schedules for Muon, NorMuon, and SOAP.\nSome AdamW bars are clipped for readability; annotations show the corresponding sync-async gap.",
                "position": 2469
            },
            {
                "img": "https://arxiv.org/html/2606.30634/2606.30634v1/figures/arxiv_plots/sweep_beta2.png",
                "caption": "Figure 12:Effect of the second-moment or variance decay coefficientβ2\\beta_{2}on synchronous and one-step delayed training on the 135M model.\nUnlike the primary momentum coefficient,β2\\beta_{2}does not produce a consistent optimizer-independent trend.\nSome bars are clipped for readability; annotations show the corresponding sync-async gap.",
                "position": 2484
            },
            {
                "img": "https://arxiv.org/html/2606.30634/2606.30634v1/figures/arxiv_plots/grid2d_muon_heatmap_abs.png",
                "caption": "Figure 13:Two-dimensional batch-size versus peak-learning-rate sweeps on the 135M model.\nFor each optimizer, we show synchronous validation loss, one-step delayed validation loss, and the sync-async gap.\nSmaller batch sizes substantially reduce the gap, but do not necessarily yield the best absolute asynchronous loss; larger batch sizes can produce large gaps, but also degrade the synchronous baseline.",
                "position": 2525
            },
            {
                "img": "https://arxiv.org/html/2606.30634/2606.30634v1/figures/arxiv_plots/grid2d_adamw_heatmap_abs.png",
                "caption": "",
                "position": 2536
            },
            {
                "img": "https://arxiv.org/html/2606.30634/2606.30634v1/figures/arxiv_plots/grid2d_soap_heatmap_abs.png",
                "caption": "",
                "position": 2543
            },
            {
                "img": "https://arxiv.org/html/2606.30634/2606.30634v1/x1.png",
                "caption": "Figure 14:Final validation loss versus the Taylor correction coefficientλ\\lambdafor DC-ASGD-style compensation on SmoLLM-135M with Muon.\nNone of the tested coefficients improves over the standard delayed baseline.",
                "position": 2565
            },
            {
                "img": "https://arxiv.org/html/2606.30634/2606.30634v1/figures/arxiv_plots/ef_lambda.png",
                "caption": "Figure 15:Final validation loss as a function of the Error-Feedback coefficientλ\\lambdaon the 135M model.\nThe valueλ=0\\lambda=0corresponds to standard delayed training without Error Feedback, whileλ=1\\lambda=1is the default correction used in the main experiments.\nThe dependence onλ\\lambdais optimizer-specific: NorMuon shows a clear U-shape with an optimum below11, while AdamW, Muon, and SOAP perform best at somewhat larger values in this sweep.\nDotted lines show the corresponding synchronous baselines.",
                "position": 2588
            },
            {
                "img": "https://arxiv.org/html/2606.30634/2606.30634v1/figures/50b-loss-lr-redacted.png",
                "caption": "Figure 16:Loss as a function of learning rate for synchronous and delayed 2B MoE training at different scales.",
                "position": 2611
            },
            {
                "img": "https://arxiv.org/html/2606.30634/2606.30634v1/figures/100b-loss-lr-redacted.png",
                "caption": "",
                "position": 2621
            },
            {
                "img": "https://arxiv.org/html/2606.30634/2606.30634v1/figures/200b-lol-redacted.png",
                "caption": "",
                "position": 2628
            },
            {
                "img": "https://arxiv.org/html/2606.30634/2606.30634v1/rebuttal_figures/cosine_sim.jpg",
                "caption": "(a)Full training dynamics.",
                "position": 2987
            },
            {
                "img": "https://arxiv.org/html/2606.30634/2606.30634v1/rebuttal_figures/cosine_sim.jpg",
                "caption": "(a)Full training dynamics.",
                "position": 2990
            },
            {
                "img": "https://arxiv.org/html/2606.30634/2606.30634v1/rebuttal_figures/cosine_sim_50.jpg",
                "caption": "(b)Zoomed-in view around delay start.",
                "position": 2995
            },
            {
                "img": "https://arxiv.org/html/2606.30634/2606.30634v1/rebuttal_figures/rel_mse.jpg",
                "caption": "(a)Full training dynamics.",
                "position": 3004
            },
            {
                "img": "https://arxiv.org/html/2606.30634/2606.30634v1/rebuttal_figures/rel_mse.jpg",
                "caption": "(a)Full training dynamics.",
                "position": 3007
            },
            {
                "img": "https://arxiv.org/html/2606.30634/2606.30634v1/rebuttal_figures/rel_mse_50.jpg",
                "caption": "(b)Zoomed-in view around delay start.",
                "position": 3012
            },
            {
                "img": "https://arxiv.org/html/2606.30634/2606.30634v1/error_feedback_on_gradients.png",
                "caption": "Figure 19:Gradient-level Error Feedback on the 135M model.\nUnlike the update-level correction used in the main experiments, applying the correction directly to raw gradients leads to divergence in our setting.",
                "position": 3093
            },
            {
                "img": "https://arxiv.org/html/2606.30634/2606.30634v1/figures/train-loss-spike-redacted.png",
                "caption": "Figure 20:The relationship between theβ2\\beta_{2}value and the loss “spike”.",
                "position": 3105
            }
        ]
    },
    {
        "header": "Appendix BAdditional Related Work: SAPipe and WPipe",
        "images": []
    },
    {
        "header": "Appendix CDelayed Stochastic Non-Euclidean Trust-Region Theory",
        "images": []
    },
    {
        "header": "Appendix DProofs for the General Theory",
        "images": []
    },
    {
        "header": "Appendix EExperimental Setup",
        "images": []
    },
    {
        "header": "Appendix FMemory and Runtime Overhead",
        "images": []
    },
    {
        "header": "Instructions for reporting errors",
        "images": []
    }
]